beatsaver/__init__.py
beatsaver/maps.py
beatsaver/playlists.py
beatsaver/search.py
beatsaver/users.py
beatsaver/vote.py
beatsaver/models/__init__.py
beatsaver/models/exceptions.py
beatsaver/models/models.py
beatsaver-1.1.0.dist-info/LICENSE
beatsaver-1.1.0.dist-info/METADATA
beatsaver-1.1.0.dist-info/WHEEL
beatsaver-1.1.0.dist-info/top_level.txt
beatsaver-1.1.0.dist-info/RECORD
