Metadata-Version: 2.1
Name: beatsaver
Version: 1.1.0
Summary: An Unofficial Python Beat Saver API Library.
Home-page: https://github.com/megamaz/beatsaver-python
Author: megamaz
Author-email: raphael.mazuel@gmail.com
License: MIT license
Project-URL: Bug Reports, https://github.com/megamaz/beatsaver-python/issues
Classifier: Development Status :: 4 - Beta
Classifier: Programming Language :: Python :: 3.12
Requires-Python: >=3.12, <4
License-File: LICENSE
